pytximport/__init__.py
pytximport/_cli.py
pytximport/_version.py
pytximport/core/__init__.py
pytximport/core/_tximport.py
pytximport/definitions/__init__.py
pytximport/importers/__init__.py
pytximport/importers/_read_kallisto.py
pytximport/importers/_read_piscem.py
pytximport/importers/_read_rsem.py
pytximport/importers/_read_salmon.py
pytximport/importers/_read_tsv.py
pytximport/utils/__init__.py
pytximport/utils/_biotype_filters.py
pytximport/utils/_convert_abundance_to_counts.py
pytximport/utils/_convert_counts_to_tpm.py
pytximport/utils/_convert_transcripts_to_genes.py
pytximport/utils/_create_transcript_gene_map.py
pytximport/utils/_filter_by_biotype.py
pytximport/utils/_get_median_length_over_isoform.py
pytximport/utils/_remove_transcript_version.py
pytximport/utils/_replace_missing_average_transcript_length.py
pytximport/utils/_replace_transcript_ids_with_names.py
pytximport/utils/_summarize_rsem_gene_data.py
pytximport-0.12.0.dist-info/entry_points.txt
pytximport-0.12.0.dist-info/licenses/LICENSE
pytximport-0.12.0.dist-info/WHEEL
pytximport-0.12.0.dist-info/METADATA
pytximport-0.12.0.dist-info/RECORD
