Metadata-Version: 2.4
Name: pytximport
Version: 0.12.0
Summary: A python implementation of `tximport` to transform transcript into gene counts
Author-email: Malte Kuehl <malte.kuehl@clin.au.dk>
Requires-Python: >=3.10
Classifier: Development Status :: 4 - Beta
Classifier: License :: OSI Approved :: GNU General Public License v3 (GPLv3)
Classifier: Intended Audience :: Science/Research
Classifier: Intended Audience :: Healthcare Industry
Classifier: Natural Language :: English
Classifier: Typing :: Typed
Classifier: Programming Language :: Python :: 3
Classifier: Programming Language :: Python :: 3.10
Classifier: Programming Language :: Python :: 3.11
Classifier: Programming Language :: Python :: 3.12
Classifier: Programming Language :: Python :: 3.13
Classifier: Operating System :: OS Independent
License-File: LICENSE
Requires-Dist: anndata>=0.8.0
Requires-Dist: click>=8.0.0,<9
Requires-Dist: click_default_group>=1.2.0,<2
Requires-Dist: flox>=0.9.0,<0.11.0
Requires-Dist: h5py>=3.0.0,<4
Requires-Dist: numpy>=1.19.0,<3
Requires-Dist: pandas>=2.2.0,<3
Requires-Dist: pybiomart==0.2.0
Requires-Dist: tqdm>=4.0.0,<5
Requires-Dist: xarray>=2024.0.0
Requires-Dist: biocframe ; extra == "biocpy"
Requires-Dist: dolomite ; extra == "biocpy"
Requires-Dist: dolomite-se ; extra == "biocpy"
Requires-Dist: summarizedexperiment ; extra == "biocpy"
Requires-Dist: bandit ; extra == "dev"
Requires-Dist: biocframe ; extra == "dev"
Requires-Dist: certifi ; extra == "dev"
Requires-Dist: coverage ; extra == "dev"
Requires-Dist: dolomite ; extra == "dev"
Requires-Dist: dolomite-se ; extra == "dev"
Requires-Dist: flit ; extra == "dev"
Requires-Dist: furo ; extra == "dev"
Requires-Dist: ipykernel ; extra == "dev"
Requires-Dist: jupyter-client ; extra == "dev"
Requires-Dist: jupyter-core ; extra == "dev"
Requires-Dist: mypy ; extra == "dev"
Requires-Dist: myst-parser ; extra == "dev"
Requires-Dist: nbsphinx ; extra == "dev"
Requires-Dist: pandas-stubs ; extra == "dev"
Requires-Dist: pandoc ; extra == "dev"
Requires-Dist: pre-commit ; extra == "dev"
Requires-Dist: pyarrow ; extra == "dev"
Requires-Dist: pytest ; extra == "dev"
Requires-Dist: ruff==0.11.2 ; extra == "dev"
Requires-Dist: sphinx ; extra == "dev"
Requires-Dist: sphinx-autoapi ; extra == "dev"
Requires-Dist: sphinx-autodoc-typehints ; extra == "dev"
Requires-Dist: sphinx-copybutton ; extra == "dev"
Requires-Dist: sphinx-design ; extra == "dev"
Requires-Dist: sphinx-rtd-theme ; extra == "dev"
Requires-Dist: summarizedexperiment ; extra == "dev"
Requires-Dist: types-tqdm ; extra == "dev"
Requires-Dist: pyarrow ; extra == "pyarrow"
Project-URL: Documentation, https://pytximport.complextissue.com/en/stable/
Project-URL: Home, https://github.com/complextissue/pytximport
Project-URL: Source, https://github.com/complextissue/pytximport
Provides-Extra: biocpy
Provides-Extra: dev
Provides-Extra: pyarrow
